{
    "mobileWidthInPercentage": 0.4037109375,
    "boxShadow": "none",
    "widgetName": "Image1",
    "displayName": "Image",
    "iconSVG": "https://appcdn.appsmith.com/static/media/icon.69b0f0dd810281fbd6e34fc2c3f39344.svg",
    "topRow": 0,
    "bottomRow": 19,
    "parentRowSpace": 10,
    "type": "IMAGE_WIDGET",
    "hideCard": false,
    "animateLoading": true,
    "parentColumnSpace": 10.671875,
    "dynamicTriggerPathList": [],
    "imageShape": "RECTANGLE",
    "leftColumn": 17,
    "dynamicBindingPathList": [{"key": "borderRadius"}],
    "defaultImage": "https://assets.appsmith.com/widgets/default.png",
    "key": "pejqxxsl73",
    "image": "https://pic.onlinewebfonts.com/thumbnails/icons_466118.svg",
    "isDeprecated": false,
    "rightColumn": 46,
    "objectFit": "cover",
    "widgetId": "g60t7u7i3q",
    "isVisible": true,
    "version": 1,
    "parentId": "0",
    "tags": ["Media"],
    "renderMode": "CANVAS",
    "isLoading": false,
    "maxZoomLevel": 1,
    "enableDownload": false,
    "borderRadius": "{{appsmith.theme.borderRadius.appBorderRadius}}",
    "enableRotation": false
}